{
  "overview": {
    "whatIs": "Docker 是一种把应用和运行环境一起“打包”的容器技术。你可以把它理解成标准化的“应用快递盒”：在你电脑能跑，在服务器上也基本能按同样方式跑，减少“我这边可以、你那边不行”的问题。",
    "keyTechnologies": [
      "Docker Engine",
      "Dockerfile",
      "Docker Compose",
      "镜像与容器管理",
      "数据卷与网络"
    ],
    "capabilities": [
      "将本地项目打包为镜像并运行",
      "用 Compose 一键启动多服务（如 Web + MySQL）",
      "独立完成单机项目部署与基础排障",
      "管理容器日志、端口、数据持久化与自动重启"
    ],
    "commonScenarios": [
      "本地开发环境快速搭建",
      "测试环境与线上环境一致化",
      "个人项目/中小服务快速部署",
      "微服务或多组件应用的本地联调"
    ],
    "quickStartPath": [
      "先安装 Docker 并跑通 hello-world",
      "掌握镜像/容器常用命令（run/ps/logs/exec）",
      "学会写 Dockerfile 打包自己的应用",
      "使用 Docker Compose 编排并部署一个完整小项目",
      "做一次从零独立部署并复盘"
    ],
    "efficientLearningTips": [
      "每次学习都要“边学边敲命令”，只看不练很难掌握",
      "把每个命令整理成自己的速查清单（含用途+示例）",
      "优先掌握 20% 高频命令，先能部署再追求高级特性",
      "每周至少做一次完整闭环：构建镜像 -> 启动容器 -> 验证 -> 查看日志 -> 修复问题"
    ]
  },
  "phases": [
    {
      "id": "phase-1",
      "title": "2周冲刺：从零到可独立部署",
      "weeks": "第1-2周",
      "goal": "在有限时间内建立 Docker 实操能力，完成一个可复用的项目部署流程，并具备基础排障能力。",
      "focus": [
        "核心概念与安装",
        "镜像/容器命令实战",
        "Dockerfile 打包",
        "Compose 编排部署",
        "独立部署复盘"
      ],
      "deliverables": [
        "个人 Docker 命令速查表（10-15条）",
        "可运行的 Dockerfile",
        "可运行的 docker-compose.yml",
        "一次独立部署记录（含问题与解决）"
      ],
      "tasks": [
        {
          "id": "t1-1-docker-concepts",
          "title": "理解 Docker 核心概念与工作流",
          "week": 1,
          "day": 1,
          "type": "学习",
          "status": "pending",
          "difficulty": "简单",
          "estimate": "35分钟",
          "objective": "理解镜像、容器、仓库、数据卷、端口映射之间的关系，建立完整心智模型。",
          "doneCriteria": "能用自己的话解释镜像和容器区别；画出“代码->镜像->容器->访问”的流程图。",
          "materials": [
            {
              "title": "Docker — 从入门到实践（中文）",
              "url": "https://yeasy.gitbook.io/docker_practice/",
              "type": "article"
            },
            {
              "title": "Docker Get Started",
              "url": "https://docs.docker.com/get-started/",
              "type": "article"
            },
            {
              "title": "What is a container?",
              "url": "https://docs.docker.com/get-started/docker-concepts/the-basics/what-is-a-container/",
              "type": "article"
            }
          ],
          "knowledgePoints": []
        },
        {
          "id": "t1-2-install-and-hello",
          "title": "安装 Docker 并跑通首个容器",
          "week": 1,
          "day": 2,
          "type": "实操",
          "status": "pending",
          "difficulty": "简单",
          "estimate": "40分钟",
          "objective": "完成 Docker 安装、权限配置和 hello-world 运行验证。",
          "doneCriteria": "终端成功执行 docker version、docker run hello-world，且无权限报错。",
          "materials": [
            {
              "title": "Install Docker Engine",
              "url": "https://docs.docker.com/engine/install/",
              "type": "article"
            },
            {
              "title": "Docker Desktop",
              "url": "https://docs.docker.com/desktop/",
              "type": "article"
            },
            {
              "title": "Linux post-installation steps",
              "url": "https://docs.docker.com/engine/install/linux-postinstall/",
              "type": "article"
            }
          ],
          "knowledgePoints": []
        },
        {
          "id": "t1-3-cli-basics",
          "title": "高频命令实操：镜像与容器管理",
          "week": 1,
          "day": 3,
          "type": "实操",
          "status": "pending",
          "difficulty": "中等",
          "estimate": "45分钟",
          "objective": "掌握 run/ps/images/pull/logs/exec/stop/rm 等命令，能独立完成容器生命周期管理。",
          "doneCriteria": "可独立完成：拉取 nginx、映射端口启动、进入容器查看文件、查看日志、停止并删除容器。",
          "materials": [
            {
              "title": "Docker CLI reference",
              "url": "https://docs.docker.com/engine/reference/commandline/docker/",
              "type": "article"
            },
            {
              "title": "Publishing and exposing ports",
              "url": "https://docs.docker.com/get-started/docker-concepts/running-containers/publishing-ports/",
              "type": "article"
            },
            {
              "title": "Persisting container data",
              "url": "https://docs.docker.com/get-started/docker-concepts/running-containers/persisting-container-data/",
              "type": "article"
            }
          ],
          "knowledgePoints": []
        },
        {
          "id": "t1-4-dockerfile",
          "title": "编写 Dockerfile 打包你的应用",
          "week": 2,
          "day": 1,
          "type": "实操",
          "status": "pending",
          "difficulty": "中等",
          "estimate": "45分钟",
          "objective": "学会使用 Dockerfile 将一个简单应用（如 Node/Python）构建成可运行镜像。",
          "doneCriteria": "完成 Dockerfile 并成功 docker build；运行容器后可通过端口访问应用。",
          "materials": [
            {
              "title": "Dockerfile 指令详解（中文）",
              "url": "https://yeasy.gitbook.io/docker_practice/image/dockerfile",
              "type": "article"
            },
            {
              "title": "Dockerfile reference",
              "url": "https://docs.docker.com/reference/dockerfile/",
              "type": "article"
            },
            {
              "title": "Building container images",
              "url": "https://docs.docker.com/get-started/docker-concepts/building-images/",
              "type": "article"
            }
          ],
          "knowledgePoints": []
        },
        {
          "id": "t1-5-compose-deploy",
          "title": "使用 Docker Compose 编排并部署多服务",
          "week": 2,
          "day": 2,
          "type": "实操",
          "status": "pending",
          "difficulty": "中等",
          "estimate": "50分钟",
          "objective": "掌握 compose.yml 基础语法，完成 Web + DB 双服务启动与联通验证。",
          "doneCriteria": "执行 docker compose up -d 成功启动两服务；应用可正常访问并连接数据库。",
          "materials": [
            {
              "title": "awesome-compose 示例仓库",
              "url": "https://github.com/docker/awesome-compose",
              "type": "article"
            },
            {
              "title": "Docker Compose overview",
              "url": "https://docs.docker.com/compose/",
              "type": "article"
            },
            {
              "title": "Getting started with Docker Compose",
              "url": "https://docs.docker.com/compose/gettingstarted/",
              "type": "article"
            },
            {
              "title": "Compose file reference",
              "url": "https://docs.docker.com/reference/compose-file/",
              "type": "article"
            }
          ],
          "knowledgePoints": []
        },
        {
          "id": "t1-6-independent-deploy-review",
          "title": "独立部署一次并复盘排障",
          "week": 2,
          "day": 3,
          "type": "复盘",
          "status": "pending",
          "difficulty": "进阶",
          "estimate": "45分钟",
          "objective": "不看教程独立完成部署，记录问题定位方法（日志、重启策略、端口冲突等）。",
          "doneCriteria": "形成一份部署复盘文档：步骤、命令、报错截图、解决方案、下次优化点。",
          "materials": [
            {
              "title": "Docker 容器实用命令（中文）",
              "url": "https://yeasy.gitbook.io/docker_practice/container",
              "type": "article"
            },
            {
              "title": "Configure logging drivers",
              "url": "https://docs.docker.com/engine/logging/configure/",
              "type": "article"
            },
            {
              "title": "Start containers automatically",
              "url": "https://docs.docker.com/engine/containers/start-containers-automatically/",
              "type": "article"
            }
          ],
          "knowledgePoints": []
        }
      ]
    }
  ],
  "currentTasks": [
    {
      "id": "task-day1-docker-basics",
      "title": "建立 Docker 核心认知（镜像/容器/仓库）",
      "type": "学习",
      "difficulty": "简单",
      "estimate": "30分钟",
      "objective": "快速理解 Docker 的基本对象和工作流程，避免后续只会命令不会原理。",
      "doneCriteria": "能口头解释 5 个关键词：image、container、registry、volume、port mapping。",
      "knowledgePoints": [
        {
          "id": "kp-image-vs-container",
          "title": "镜像与容器的区别",
          "description": "镜像是只读模板，容器是镜像运行后的实例；一个镜像可启动多个容器。",
          "materials": [
            {
              "title": "What is a container?",
              "url": "https://docs.docker.com/get-started/docker-concepts/the-basics/what-is-a-container/",
              "type": "article"
            }
          ]
        },
        {
          "id": "kp-docker-workflow",
          "title": "典型工作流",
          "description": "开发代码 -> 编写 Dockerfile -> build 镜像 -> run 容器 -> 通过日志/端口验证。",
          "materials": [
            {
              "title": "Docker Get Started",
              "url": "https://docs.docker.com/get-started/",
              "type": "article"
            }
          ]
        }
      ],
      "materials": [
        {
          "title": "Docker — 从入门到实践（中文）",
          "url": "https://yeasy.gitbook.io/docker_practice/",
          "type": "article"
        },
        {
          "title": "Docker Get Started",
          "url": "https://docs.docker.com/get-started/",
          "type": "article"
        },
        {
          "title": "What is a container?",
          "url": "https://docs.docker.com/get-started/docker-concepts/the-basics/what-is-a-container/",
          "type": "article"
        }
      ]
    },
    {
      "id": "task-day3-install-verify",
      "title": "完成安装并验证 Docker 可用",
      "type": "实操",
      "difficulty": "简单",
      "estimate": "40分钟",
      "objective": "在你的本机完成安装、权限配置并跑通 hello-world。",
      "doneCriteria": "执行 docker version 与 docker run hello-world 成功；保存终端截图。",
      "knowledgePoints": [
        {
          "id": "kp-install-path",
          "title": "不同平台安装路径",
          "description": "Windows/macOS 常用 Docker Desktop；Linux 常用 Docker Engine。",
          "materials": [
            {
              "title": "Docker Desktop",
              "url": "https://docs.docker.com/desktop/",
              "type": "article"
            },
            {
              "title": "Install Docker Engine",
              "url": "https://docs.docker.com/engine/install/",
              "type": "article"
            }
          ]
        },
        {
          "id": "kp-linux-permission",
          "title": "Linux 权限与 post-install",
          "description": "将当前用户加入 docker 组，避免每次都用 sudo。",
          "materials": [
            {
              "title": "Linux post-installation steps",
              "url": "https://docs.docker.com/engine/install/linux-postinstall/",
              "type": "article"
            }
          ]
        }
      ],
      "materials": [
        {
          "title": "Install Docker Engine",
          "url": "https://docs.docker.com/engine/install/",
          "type": "article"
        },
        {
          "title": "Linux post-installation steps",
          "url": "https://docs.docker.com/engine/install/linux-postinstall/",
          "type": "article"
        },
        {
          "title": "Docker Desktop",
          "url": "https://docs.docker.com/desktop/",
          "type": "article"
        }
      ]
    },
    {
      "id": "task-day6-cli-practice",
      "title": "高频命令 1 小时实战",
      "type": "实操",
      "difficulty": "中等",
      "estimate": "45分钟",
      "objective": "掌握容器从创建到删除的完整生命周期操作。",
      "doneCriteria": "独立完成：pull nginx -> run -p -> logs -> exec -> stop -> rm；并记录命令清单。",
      "knowledgePoints": [
        {
          "id": "kp-container-lifecycle",
          "title": "容器生命周期命令",
          "description": "重点练习 run/ps/logs/exec/stop/start/rm，建立排障最小闭环。",
          "materials": [
            {
              "title": "Docker CLI reference",
              "url": "https://docs.docker.com/engine/reference/commandline/docker/",
              "type": "article"
            }
          ]
        },
        {
          "id": "kp-port-volume",
          "title": "端口映射与数据持久化",
          "description": "端口决定访问方式，volume 决定数据是否随容器删除而丢失。",
          "materials": [
            {
              "title": "Publishing and exposing ports",
              "url": "https://docs.docker.com/get-started/docker-concepts/running-containers/publishing-ports/",
              "type": "article"
            },
            {
              "title": "Persisting container data",
              "url": "https://docs.docker.com/get-started/docker-concepts/running-containers/persisting-container-data/",
              "type": "article"
            }
          ]
        }
      ],
      "materials": [
        {
          "title": "Docker CLI reference",
          "url": "https://docs.docker.com/engine/reference/commandline/docker/",
          "type": "article"
        },
        {
          "title": "Persisting container data",
          "url": "https://docs.docker.com/get-started/docker-concepts/running-containers/persisting-container-data/",
          "type": "article"
        },
        {
          "title": "Publishing and exposing ports",
          "url": "https://docs.docker.com/get-started/docker-concepts/running-containers/publishing-ports/",
          "type": "article"
        }
      ]
    }
  ]
}